msgpack_white/__init__.py
msgpack_white/__init__.pyi
msgpack_white/_white.cpython-310-i386-linux-gnu.so
msgpack_white/py.typed
msgpack_white-1.0.0.dist-info/METADATA
msgpack_white-1.0.0.dist-info/WHEEL
msgpack_white-1.0.0.dist-info/top_level.txt
msgpack_white-1.0.0.dist-info/RECORD
msgpack_white-1.0.0.dist-info/licenses/LICENSE
