Metadata-Version: 2.4
Name: msgpack-white
Version: 1.0.0
Summary: Determine the end of MessagePack data quickly
Author-email: Alex Kirchhoff <py-msgpack-white@kirchhoff.digital>
Maintainer-email: Alex Kirchhoff <py-msgpack-white@kirchhoff.digital>
License-Expression: BSD-3-Clause
Keywords: msgpack,MessagePack
Classifier: Development Status :: 5 - Production/Stable
Classifier: Intended Audience :: Developers
Classifier: Operating System :: OS Independent
Classifier: Programming Language :: Python :: 3
Classifier: Programming Language :: Python :: 3.9
Classifier: Programming Language :: Python :: 3.10
Classifier: Programming Language :: Python :: 3.11
Classifier: Programming Language :: Python :: 3.12
Classifier: Programming Language :: Python :: 3.13
Classifier: Topic :: File Formats
Classifier: Typing :: Typed
Requires-Python: >=3.9
License-File: LICENSE
Dynamic: license-file
